{
    "ads": [
        {
            "type": "VastXml",
            "content": "<VAST version=\"3.0\"><Ad id=\"60876\"><Wrapper><AdSystem>Teads Technology</AdSystem><VASTAdTagURI><![CDATA[https://s8t.teads.tv/vast/6753877076839092]]></VASTAdTagURI><Error><![CDATA[https://t.teads.tv/track?action=error-vast&vid=979db8c1-bb01-4ff7-ad59-bf7a87802c20&gid=197012&code=[ERRORCODE]&cid=176308&pid=84242&auctid=f65b3645-e382-4d00-bd96-372ca191ba58&be=1&mediaFileType=[MEDIAFILETYPE]]]></Error><Impression><![CDATA[https://t.teads.tv/track?action=impression&vid=979db8c1-bb01-4ff7-ad59-bf7a87802c20&gid=197012&piv=[VIEWABILITY]&cid=176308&pid=84242&auctid=f65b3645-e382-4d00-bd96-372ca191ba58&be=1&mediaFileType=[MEDIAFILETYPE]]]></Impression><Creatives><Creative id=\"176308\"><Linear><Icons><Icon program=\"\" width=\"0\" height=\"0\" xPosition=\"\" yPosition=\"\"><IFrameResource><![CDATA[]]></IFrameResource><IconClicks><IconClickTracking><![CDATA[https://t.teads.tv/track?action=clickIcon&vid=979db8c1-bb01-4ff7-ad59-bf7a87802c20&gid=197012&cid=176308&pid=84242&auctid=f65b3645-e382-4d00-bd96-372ca191ba58&be=1]]></IconClickTracking><IconClickThrough><![CDATA[https://teads.tv/privacy-policy/]]></IconClickThrough></IconClicks></Icon></Icons><TrackingEvents><Tracking event=\"start\"><![CDATA[https://t.teads.tv/track?action=start&vid=979db8c1-bb01-4ff7-ad59-bf7a87802c20&gid=197012&piv=[VIEWABILITY]&cid=176308&pid=84242&auctid=f65b3645-e382-4d00-bd96-372ca191ba58&be=1&cph=[CONTENTPLAYHEAD]&cost_curr=EUR&cost=_C6kvCmUcNJIJzKX-iI4upnB&erevenue=yJf6266yoxHFwR5KfA3GqqUJ&brid=2&erevenue_curr=EUR&analyticsOnly=false]]></Tracking><Tracking event=\"firstQuartile\"><![CDATA[https://t.teads.tv/track?action=firstQuartile&vid=979db8c1-bb01-4ff7-ad59-bf7a87802c20&gid=197012&piv=[VIEWABILITY]&cid=176308&pid=84242&auctid=f65b3645-e382-4d00-bd96-372ca191ba58&be=1&cph=[CONTENTPLAYHEAD]]]></Tracking><Tracking event=\"midpoint\"><![CDATA[https://t.teads.tv/track?action=midpoint&vid=979db8c1-bb01-4ff7-ad59-bf7a87802c20&gid=197012&piv=[VIEWABILITY]&cid=176308&pid=84242&auctid=f65b3645-e382-4d00-bd96-372ca191ba58&be=1&cph=[CONTENTPLAYHEAD]]]></Tracking><Tracking event=\"thirdQuartile\"><![CDATA[https://t.teads.tv/track?action=thirdQuartile&vid=979db8c1-bb01-4ff7-ad59-bf7a87802c20&gid=197012&piv=[VIEWABILITY]&cid=176308&pid=84242&auctid=f65b3645-e382-4d00-bd96-372ca191ba58&be=1&cph=[CONTENTPLAYHEAD]]]></Tracking><Tracking event=\"complete\"><![CDATA[https://t.teads.tv/track?action=complete&vid=979db8c1-bb01-4ff7-ad59-bf7a87802c20&gid=197012&piv=[VIEWABILITY]&cid=176308&pid=84242&auctid=f65b3645-e382-4d00-bd96-372ca191ba58&be=1&cph=[CONTENTPLAYHEAD]&revenue=I6cfPMqDbp70DowT4axAF5rr&revenue_curr=EUR&analyticsOnly=false]]></Tracking><Tracking event=\"pause\"><![CDATA[https://t.teads.tv/track?action=pause&vid=979db8c1-bb01-4ff7-ad59-bf7a87802c20&gid=197012&piv=[VIEWABILITY]&cid=176308&pid=84242&auctid=f65b3645-e382-4d00-bd96-372ca191ba58&be=1&cph=[CONTENTPLAYHEAD]]]></Tracking><Tracking event=\"resume\"><![CDATA[https://t.teads.tv/track?action=resume&vid=979db8c1-bb01-4ff7-ad59-bf7a87802c20&gid=197012&piv=[VIEWABILITY]&cid=176308&pid=84242&auctid=f65b3645-e382-4d00-bd96-372ca191ba58&be=1&cph=[CONTENTPLAYHEAD]]]></Tracking><Tracking event=\"mute\"><![CDATA[https://t.teads.tv/track?action=mute&vid=979db8c1-bb01-4ff7-ad59-bf7a87802c20&gid=197012&piv=[VIEWABILITY]&cid=176308&pid=84242&auctid=f65b3645-e382-4d00-bd96-372ca191ba58&be=1&cph=[CONTENTPLAYHEAD]]]></Tracking><Tracking event=\"unmute\"><![CDATA[https://t.teads.tv/track?action=unmute&vid=979db8c1-bb01-4ff7-ad59-bf7a87802c20&gid=197012&piv=[VIEWABILITY]&cid=176308&pid=84242&auctid=f65b3645-e382-4d00-bd96-372ca191ba58&be=1&cph=[CONTENTPLAYHEAD]]]></Tracking><Tracking event=\"expand\"><![CDATA[https://t.teads.tv/track?action=expand&vid=979db8c1-bb01-4ff7-ad59-bf7a87802c20&gid=197012&piv=[VIEWABILITY]&cid=176308&pid=84242&auctid=f65b3645-e382-4d00-bd96-372ca191ba58&be=1&cph=[CONTENTPLAYHEAD]]]></Tracking><Tracking event=\"collapse\"><![CDATA[https://t.teads.tv/track?action=collapse&vid=979db8c1-bb01-4ff7-ad59-bf7a87802c20&gid=197012&piv=[VIEWABILITY]&cid=176308&pid=84242&auctid=f65b3645-e382-4d00-bd96-372ca191ba58&be=1&cph=[CONTENTPLAYHEAD]]]></Tracking><Tracking event=\"rewind\"><![CDATA[https://t.teads.tv/track?action=rewind&vid=979db8c1-bb01-4ff7-ad59-bf7a87802c20&gid=197012&piv=[VIEWABILITY]&cid=176308&pid=84242&auctid=f65b3645-e382-4d00-bd96-372ca191ba58&be=1&cph=[CONTENTPLAYHEAD]]]></Tracking><Tracking event=\"skip\"><![CDATA[https://t.teads.tv/track?action=skip&vid=979db8c1-bb01-4ff7-ad59-bf7a87802c20&gid=197012&piv=[VIEWABILITY]&cid=176308&pid=84242&auctid=f65b3645-e382-4d00-bd96-372ca191ba58&be=1&cph=[CONTENTPLAYHEAD]]]></Tracking><Tracking event=\"close\"><![CDATA[https://t.teads.tv/track?action=close&vid=979db8c1-bb01-4ff7-ad59-bf7a87802c20&gid=197012&piv=[VIEWABILITY]&cid=176308&pid=84242&auctid=f65b3645-e382-4d00-bd96-372ca191ba58&be=1&cph=[CONTENTPLAYHEAD]]]></Tracking></TrackingEvents><VideoClicks><ClickTracking><![CDATA[https://t.teads.tv/track?action=click&vid=979db8c1-bb01-4ff7-ad59-bf7a87802c20&cid=176308&gid=197012&pid=84242&1522844541062&be=1&cph=[CONTENTPLAYHEAD]&piv=[VIEWABILITY]&auctid=f65b3645-e382-4d00-bd96-372ca191ba58]]></ClickTracking></VideoClicks></Linear></Creative></Creatives><Extensions></Extensions></Wrapper></Ad></VAST>",
            "scenario_id": 9145,
            "insertion_id": 197012
        }
    ]
}